sensory_cloud/__init__.py
sensory_cloud/config.py
sensory_cloud/initializer.py
sensory_cloud/token_manager.py
sensory_cloud/generated/__init__.py
sensory_cloud/generated/common/__init__.py
sensory_cloud/generated/common/common_pb2.py
sensory_cloud/generated/common/common_pb2_grpc.py
sensory_cloud/generated/health/__init__.py
sensory_cloud/generated/health/health_pb2.py
sensory_cloud/generated/health/health_pb2_grpc.py
sensory_cloud/generated/oauth/__init__.py
sensory_cloud/generated/oauth/oauth_pb2.py
sensory_cloud/generated/oauth/oauth_pb2_grpc.py
sensory_cloud/generated/v1/__init__.py
sensory_cloud/generated/v1/assistant/__init__.py
sensory_cloud/generated/v1/assistant/assistant_pb2.py
sensory_cloud/generated/v1/assistant/assistant_pb2_grpc.py
sensory_cloud/generated/v1/audio/__init__.py
sensory_cloud/generated/v1/audio/audio_pb2.py
sensory_cloud/generated/v1/audio/audio_pb2_grpc.py
sensory_cloud/generated/v1/event/__init__.py
sensory_cloud/generated/v1/event/event_pb2.py
sensory_cloud/generated/v1/event/event_pb2_grpc.py
sensory_cloud/generated/v1/file/__init__.py
sensory_cloud/generated/v1/file/file_pb2.py
sensory_cloud/generated/v1/file/file_pb2_grpc.py
sensory_cloud/generated/v1/management/__init__.py
sensory_cloud/generated/v1/management/device_pb2.py
sensory_cloud/generated/v1/management/device_pb2_grpc.py
sensory_cloud/generated/v1/management/enrollment_pb2.py
sensory_cloud/generated/v1/management/enrollment_pb2_grpc.py
sensory_cloud/generated/v1/video/__init__.py
sensory_cloud/generated/v1/video/video_pb2.py
sensory_cloud/generated/v1/video/video_pb2_grpc.py
sensory_cloud/generated/validate/__init__.py
sensory_cloud/generated/validate/validate_pb2.py
sensory_cloud/generated/validate/validate_pb2_grpc.py
sensory_cloud/services/__init__.py
sensory_cloud/services/assistant_service.py
sensory_cloud/services/audio_service.py
sensory_cloud/services/crypto_service.py
sensory_cloud/services/health_service.py
sensory_cloud/services/management_service.py
sensory_cloud-1.0.2.dist-info/LICENSE.txt
sensory_cloud-1.0.2.dist-info/METADATA
sensory_cloud-1.0.2.dist-info/WHEEL
sensory_cloud-1.0.2.dist-info/top_level.txt
sensory_cloud-1.0.2.dist-info/RECORD
