Metadata-Version: 2.1
Name: sensory-cloud
Version: 1.0.2
Summary: Python SDK for Sensory Cloud
Home-page: https://github.com/Sensory-Cloud/python-sdk
Author: Jonathan Hersch
Author-email: jhersch@sensoryinc.com
Requires-Python: >=3.6
License-File: LICENSE.txt
Requires-Dist: certifi (==2021.10.8)
Requires-Dist: grpcio (==1.42.0)
Requires-Dist: grpcio-tools (==1.42.0)
Requires-Dist: protobuf (==3.19.1)
Requires-Dist: six (==1.16.0)
Requires-Dist: pycparser (==2.21)
Requires-Dist: PyJWT (==2.4.0)
Requires-Dist: cryptography (==37.0.2)
